lamindb/__init__.py
lamindb/_finish.py
lamindb/_tracked.py
lamindb/_view.py
lamindb/errors.py
lamindb/py.typed
lamindb/base/__init__.py
lamindb/base/dtypes.py
lamindb/base/fields.py
lamindb/base/ids.py
lamindb/base/types.py
lamindb/base/uids.py
lamindb/base/users.py
lamindb/base/utils.py
lamindb/core/__init__.py
lamindb/core/_compat.py
lamindb/core/_context.py
lamindb/core/_mapped_collection.py
lamindb/core/_settings.py
lamindb/core/_sync_git.py
lamindb/core/_track_environment.py
lamindb/core/exceptions.py
lamindb/core/loaders.py
lamindb/core/types.py
lamindb/core/storage/__init__.py
lamindb/core/storage/_anndata_accessor.py
lamindb/core/storage/_backed_access.py
lamindb/core/storage/_polars_lazy_df.py
lamindb/core/storage/_pyarrow_dataset.py
lamindb/core/storage/_spatialdata_accessor.py
lamindb/core/storage/_tiledbsoma.py
lamindb/core/storage/_valid_suffixes.py
lamindb/core/storage/_zarr.py
lamindb/core/storage/objects.py
lamindb/core/storage/paths.py
lamindb/core/subsettings/__init__.py
lamindb/core/subsettings/_annotation_settings.py
lamindb/core/subsettings/_creation_settings.py
lamindb/curators/__init__.py
lamindb/curators/_legacy.py
lamindb/curators/core.py
lamindb/examples/__init__.py
lamindb/examples/cellxgene/__init__.py
lamindb/examples/cellxgene/_cellxgene.py
lamindb/examples/cellxgene/cellxgene_schema_versions.csv
lamindb/examples/croissant/__init__.py
lamindb/examples/croissant/mini_immuno.anndata.zarr_metadata.json
lamindb/examples/datasets/__init__.py
lamindb/examples/datasets/_core.py
lamindb/examples/datasets/_fake.py
lamindb/examples/datasets/_small.py
lamindb/examples/datasets/define_mini_immuno_features_labels.py
lamindb/examples/datasets/define_mini_immuno_schema_flexible.py
lamindb/examples/datasets/mini_immuno.py
lamindb/examples/datasets/save_mini_immuno_datasets.py
lamindb/examples/fixtures/__init__.py
lamindb/examples/fixtures/sheets.py
lamindb/examples/mlflow/__init__.py
lamindb/examples/schemas/__init__.py
lamindb-1.17.0.dist-info/LICENSE
lamindb-1.17.0.dist-info/WHEEL
lamindb-1.17.0.dist-info/METADATA
lamindb-1.17.0.dist-info/RECORD
