Metadata-Version: 2.3
Name: lamindb
Version: 1.17.0
Summary: A data framework for biology.
Author-email: Lamin Labs <open-source@lamin.ai>
Requires-Python: >=3.10,<3.14
Classifier: Programming Language :: Python :: 3.10
Classifier: Programming Language :: Python :: 3.11
Classifier: Programming Language :: Python :: 3.12
Classifier: Programming Language :: Python :: 3.13
Requires-Dist: lamin_utils==0.16.2
Requires-Dist: lamin_cli==1.10.0
Requires-Dist: lamindb_setup[aws]==1.17.0
Requires-Dist: bionty==1.10.0
Requires-Dist: wetlab==1.6.1
Requires-Dist: jupytext
Requires-Dist: nbconvert>=7.2.1
Requires-Dist: nbproject==0.11.1
Requires-Dist: pyyaml
Requires-Dist: pyarrow
Requires-Dist: pandera>=0.24.0
Requires-Dist: typing_extensions!=4.6.0
Requires-Dist: python-dateutil
Requires-Dist: pandas>=2.0.0,<3.0.0
Requires-Dist: anndata>=0.8.0,<=0.12.5
Requires-Dist: fsspec
Requires-Dist: graphviz
Requires-Dist: psycopg2-binary
Requires-Dist: tomlkit ; extra == "dev"
Requires-Dist: line_profiler ; extra == "dev"
Requires-Dist: pre-commit ; extra == "dev"
Requires-Dist: nox ; extra == "dev"
Requires-Dist: laminci>=0.3 ; extra == "dev"
Requires-Dist: pytest>=6.0 ; extra == "dev"
Requires-Dist: coverage ; extra == "dev"
Requires-Dist: pytest-cov<7.0.0 ; extra == "dev"
Requires-Dist: mudata ; extra == "dev"
Requires-Dist: nbproject_test>=0.6.0 ; extra == "dev"
Requires-Dist: faker-biology ; extra == "dev"
Requires-Dist: pronto ; extra == "dev"
Requires-Dist: readfcs>=2.0.1 ; extra == "fcs"
Requires-Dist: lamindb_setup[gcp] ; extra == "gcp"
Requires-Dist: numcodecs<0.16.0 ; extra == "zarr"
Requires-Dist: zarr>=2.16.0,<3.0.0a0 ; extra == "zarr"
Project-URL: Home, https://github.com/laminlabs/lamindb
Provides-Extra: dev
Provides-Extra: fcs
Provides-Extra: gcp
Provides-Extra: zarr
